{
  "ProductID": "FDAWCPDC010",
  "SKU": "DIP-COATING-DIP",
  "Name": "ADJ WRENCH 10 INCH BCP GREEN DIP COATING",
  "ItemName": "Adjustable Wrench 10\" Green Grip",
  "Slug": "adj-wrench-10-inch-bcp-green-dip-coating",
  "Category": "hand-tools",
  "Subcategory": "Hand Tool",
  "Brand": "Eastman",
  "Images": [
    "https://www.eastmanshop.com/cdn/shop/files/1_29_9_600x600.jpg?v=1755949471"
  ],
  "Image": "https://www.eastmanshop.com/cdn/shop/files/1_29_9_600x600.jpg?v=1755949471",
  "Description": "",
  "DetailedInfo": "",
  "StockQuantity": 1,
  "Unit": "pc",
  "MRP": 504,
  "Discount": 25,
  "SalePrice": 376,
  "Supplier": "Eastman",
  "LastUpdated": "24/03/2026",
  "ProductURL": "https://www.haryanatools.com/product/adj-wrench-10-inch-bcp-green-dip-coating",
  "Model": "",
  "Country": "",
  "ASIN": "",
  "SearchKeywords": "",
  "VideoURL": ""
}
