{
  "ProductID": "KIT-E2406-08D",
  "SKU": "E-2406",
  "Name": "Eastman ALLEN KEY SET BLACK COLOUR CHAMPHERED HERADS XTRA LONG 1.5 2 2.5 3 4 5 6 8 10 Mm KE EAK 2406",
  "ItemName": "Extra Long Allen Key Set 9 Pcs Metric",
  "Slug": "eastman-allen-key-set-black-colour-champhered-herads-xtra-long-15-2-25-3-4-5-6-8-10-mm-ke-eak-2406",
  "Category": "hand-tools",
  "Subcategory": "Hand Tool",
  "Brand": "Eastman",
  "Images": [
    "https://www.eastmanshop.com/cdn/shop/files/2_27_17_600x600.jpg?v=1755949419",
    "https://www.eastmanshop.com/cdn/shop/files/tools2_0000s_0001_26_add26a4d-2eff-41e6-b6f0-c7307a6471a0_600x600.jpg?v=1755949419"
  ],
  "Image": "https://www.eastmanshop.com/cdn/shop/files/2_27_17_600x600.jpg?v=1755949419",
  "Description": "",
  "DetailedInfo": "",
  "StockQuantity": 1,
  "Unit": "pc",
  "MRP": 672,
  "Discount": 26,
  "SalePrice": 500,
  "Supplier": "Eastman",
  "LastUpdated": "24/03/2026",
  "ProductURL": "",
  "Model": "",
  "Country": "",
  "ASIN": "",
  "SearchKeywords": "",
  "VideoURL": ""
}
