{
  "ProductID": "FIDSE2202B24R1",
  "SKU": "R1-E-2202-R1",
  "Name": "Eastman 1 2 Sq. Drive Socket Sets Set 24Pcs 19 + 5 Accessories Chrome Vanadium Steel E 2202 624 R1 HEX",
  "ItemName": "1/2\" Drive Socket Set 24 Pcs",
  "Slug": "eastman-1-2-sq-drive-socket-sets-set-24pcs-19-5-accessories-chrome-vanadium-steel-e-2202-624-r1-hex",
  "Category": "hand-tools",
  "Subcategory": "Hand Tool",
  "Brand": "Eastman",
  "Images": [
    "https://m.media-amazon.com/images/I/41Plx2pyIGL._SX38_SY50_CR,0,0,38,50_.jpg",
    "https://m.media-amazon.com/images/I/41upsFS93FL._SX38_SY50_CR,0,0,38,50_.jpg",
    "https://m.media-amazon.com/images/I/51TXo52J2tL._SX38_SY50_CR,0,0,38,50_.jpg",
    "https://m.media-amazon.com/images/I/41-32IcT9lL._SX38_SY50_CR,0,0,38,50_.jpg",
    "https://m.media-amazon.com/images/I/41GLYFrj4pL._SX38_SY50_CR,0,0,38,50_.jpg"
  ],
  "Image": "https://m.media-amazon.com/images/I/41Plx2pyIGL._SX38_SY50_CR,0,0,38,50_.jpg",
  "Description": "Eastman 24 Pcs. 1/2 Inch Square Drive Socket Set E-2202 online in India at wholesale rates. If you have been looking for Eastman 24 Pcs. 1/2 Inch Square Drive Socket Set E-2202 dealers, your search ends here as you can get the best Eastman 24 Pcs. 1/2 Inch Square Drive Socket Set E-2202 distributors in top cities such as Delhi NCR, Mumbai, Chennai, Pune, Jaipur, Hyderabad and Ahmedabad. You can purchase Eastman 24 Pcs. 1/2 Inch Square Drive Socket Set E-2202 of the finest quality and rest assured to get the best in terms of both durability and performance. If you are bothered about the Eastman 24 Pcs. 1/2 Inch Square Drive Socket Set E-2202 prices, you can be totally sure to get the best rates as we brings you genuine Eastman 24 Pcs. 1/2 Inch Square Drive Socket Set E-2202 rates and quality assured products only from the best of brands with exclusive brand discounts you won’t find anywhere else. Procure Eastman 24 Pcs. 1/2 Inch Square Drive Socket Set E-2202 today and avail the best of",
  "DetailedInfo": "Drive System: Square | Drive Bit Application: general | Drive End Style: Hex Shank | Drive Bit Shank Style: Square | Bit Compatibilities: 1/2 inch hex | Number Of Pieces: 24 | Material Type: Chrome Vanadium Steel | Finish Types: Satin Finish | Brand Name: Eastman | Model Number: E-2202_E-624-R1 | Set Name: Socket Sets | Manufacturer: Eastman, Eastman | Manufacturer Part Number: E-2202_E-624-R1 | Packer Contact Information: Evytaa Lifestyle Private Limited | Item Type Name: Hammer | Included Components: Case | Manufacturer Contact Information: Eastman | Item Weight: 2500 Grams | Country Of Publication: India | Unit Count: 1.0 Count | Best Sellers Rank: #248,482 in Home Improvement (See Top 100 in Home Improvement)#298 inSquare Drive Sockets | Asin: B09F9FNB3F | Customer Reviews: 1.01.0 out of 5 stars(2)1.0 out of 5 stars",
  "StockQuantity": 1,
  "Unit": "pc",
  "MRP": 5820,
  "Discount": 34.6,
  "SalePrice": 3807,
  "Supplier": "Eastman",
  "LastUpdated": "24/03/2026",
  "ProductURL": "https://www.haryana.tools/product/R1-E-2202-R1",
  "Model": "E-2202_E-624-R1",
  "Country": "India",
  "ASIN": "B09F9FNB3F",
  "SearchKeywords": -2,
  "VideoURL": ""
}
