{
  "ProductID": "FITSE000100E20",
  "SKU": "E-2228-E20",
  "Name": "STAR SOCKET E20 E 2228",
  "ItemName": "Star Socket E20",
  "Slug": "star-socket-e20-e-2228",
  "Category": "hand-tools",
  "Subcategory": "Hand Tool",
  "Brand": "Eastman",
  "Images": [
    "https://www.eastmanshop.com/cdn/shop/files/3_95ad4cd4-fd44-4951-8fdd-af7a58270c75_1400x1400.jpg?v=1755949237",
    "https://www.eastmanshop.com/cdn/shop/files/2_072e5313-6d54-4c31-b380-028fca9bd05a_1400x1400.jpg?v=1755949237",
    "https://www.eastmanshop.com/cdn/shop/files/1_2abfabe2-f176-4070-85c8-bf16be462cad_1400x1400.jpg?v=1755949237"
  ],
  "Image": "https://www.eastmanshop.com/cdn/shop/files/3_95ad4cd4-fd44-4951-8fdd-af7a58270c75_1400x1400.jpg?v=1755949237",
  "Description": "",
  "DetailedInfo": "",
  "StockQuantity": 1,
  "Unit": "pc",
  "MRP": 178,
  "Discount": 25,
  "SalePrice": 134,
  "Supplier": "Eastman",
  "LastUpdated": "24/03/2026",
  "ProductURL": "",
  "Model": "",
  "Country": "",
  "ASIN": "",
  "SearchKeywords": "",
  "VideoURL": ""
}
