{
  "ProductID": "FAPEWCB0075M10",
  "SKU": "EWCB0075M10",
  "Name": "TWISTED WIRE CUP BRUSH 75MM M10",
  "ItemName": "Twisted Wire Cup Brush 75mm M10",
  "Slug": "twisted-wire-cup-brush-75mm-m10",
  "Category": "power-tools",
  "Subcategory": "Power Accessories",
  "Brand": "Eastman",
  "Images": [
    "https://www.eastmanshop.com/cdn/shop/files/EWCB75M10_02546f1a-90cb-4059-913f-eb9c0dc7f034_1400x1400.jpg?v=1755949207"
  ],
  "Image": "https://www.eastmanshop.com/cdn/shop/files/EWCB75M10_02546f1a-90cb-4059-913f-eb9c0dc7f034_1400x1400.jpg?v=1755949207",
  "Description": "",
  "DetailedInfo": "",
  "StockQuantity": 80,
  "Unit": "PC",
  "MRP": 296,
  "Discount": 48,
  "SalePrice": 155,
  "Supplier": "Eastman",
  "LastUpdated": "24/03/2026",
  "ProductURL": "",
  "Model": "",
  "Country": "",
  "ASIN": "",
  "SearchKeywords": "",
  "VideoURL": ""
}
