{
  "Title": "Best Hardware Store in Pehowa for Industrial & Home Projects",
  "Slug": "best-hardware-store-pehowa",
  "Author": "JK Enterprises",
  "Date": "",
  "Category": "Local SEO",
  "Tags": [
    "hardware pehowa",
    "hardware store",
    "industrial hardware"
  ],
  "MarkdownFile": "best-hardware-store-pehowa.md",
  "FeaturedImage": "",
  "RelatedProducts": [],
  "SEOTitle": "Best Hardware Store in Pehowa for Industrial & Home Projects",
  "MetaDescription": "",
  "CanonicalURL": "blog.html?slug=best-hardware-store-pehowa"
}
