{
  "Title": "How China's Import Duties Affect Power Tool Prices in India",
  "Slug": "china-import-duty-tool-prices",
  "Author": "JK Enterprises",
  "Date": 46220,
  "Category": "Industry News",
  "Tags": [
    "china imports",
    "import duty",
    "industrial tools",
    "trade"
  ],
  "MarkdownFile": "china-import-duty-tool-prices.md",
  "FeaturedImage": "",
  "RelatedProducts": [],
  "SEOTitle": "China Import Duty and Power Tool Prices",
  "MetaDescription": "Import duties and global trade policies can directly impact industrial equipment pricing.",
  "CanonicalURL": "https://www.haryana.tools/blog.html?id=china-import-duty-tool-prices"
}
